egolocal
egorovsystem
egoserver
egoserver_setnginx
