Metadata-Version: 2.4
Name: egorovsystem
Version: 0.0.9.post10
Author: Yongyi Yang
Author-email: yongyi@umich.edu
License: MIT License
Requires-Python: >=3.6
License-File: LICENSE
Requires-Dist: YYYTools>=0.1.6
Requires-Dist: django
Requires-Dist: gunicorn
Requires-Dist: whitenoise
Dynamic: author
Dynamic: author-email
Dynamic: description
Dynamic: description-content-type
Dynamic: license
Dynamic: license-file
Dynamic: requires-dist
Dynamic: requires-python
